Metadata-Version: 2.4
Name: zk-chat
Version: 3.5.1
Summary: zk-chat is a command-line chat tool for your zettelkasten
Author-email: Stacey Vetzal <stacey@vetzal.com>
Project-URL: Homepage, https://github.com/svetzal/zk-chat
Project-URL: Issues, https://github.com/svetzal/zk-chat/issues
Classifier: Programming Language :: Python :: 3
Classifier: License :: OSI Approved :: MIT License
Classifier: Operating System :: OS Independent
Requires-Python: >=3.11
Requires-Dist: chromadb>=1.1.0
Requires-Dist: pyyaml
Requires-Dist: mojentic>=0.8.2
Requires-Dist: PySide6>=6.6.0
Requires-Dist: rich
Requires-Dist: typer[all]>=0.9.0
Requires-Dist: fastmcp>=2.0.0
Provides-Extra: dev
Requires-Dist: ruff; extra == "dev"
Requires-Dist: pytest; extra == "dev"
Requires-Dist: pytest-spec; extra == "dev"
Requires-Dist: pytest-cov; extra == "dev"
Requires-Dist: pytest-mock; extra == "dev"
Requires-Dist: mkdocs; extra == "dev"
Requires-Dist: mkdocs-material; extra == "dev"
Requires-Dist: pymdown-extensions; extra == "dev"
